time_series_dataset/__init__.py
time_series_dataset/time_series_dataset.py
time_series_dataset-0.0.9.dist-info/LICENSE
time_series_dataset-0.0.9.dist-info/METADATA
time_series_dataset-0.0.9.dist-info/WHEEL
time_series_dataset-0.0.9.dist-info/top_level.txt
time_series_dataset-0.0.9.dist-info/RECORD
