Metadata-Version: 2.1
Name: time-series-dataset
Version: 0.0.9
Summary: Time series dataset for torch.
Home-page: https://github.com/krypton-unite/time_series_dataset.git
Author: Daniel Kaminski de Souza
Author-email: daniel@kryptonunite.com
License: The Unlicense
Download-URL: https://pypi.org/project/time-series-dataset/
Keywords: Time series dataset
Platform: UNKNOWN
Requires-Dist: torch
Provides-Extra: dev
Requires-Dist: bumpversion ; extra == 'dev'
Requires-Dist: twine ; extra == 'dev'
Requires-Dist: wheel ; extra == 'dev'
Provides-Extra: test
Requires-Dist: pandas ; extra == 'test'
Requires-Dist: pytest ; extra == 'test'
Requires-Dist: pytest-cov ; extra == 'test'
Requires-Dist: seaborn ; extra == 'test'
